procyon/__init__.py
procyon/__version__.py
procyon/button.py
procyon/checkBox.py
procyon/colors.py
procyon/container.py
procyon/element.py
procyon/keybinds.py
procyon/label.py
procyon/menu.py
procyon/panel.py
procyon/progressBar.py
procyon/rowBar.py
procyon/textField.py
procyon/uiManager.py
procyon_py-0.3.7.dist-info/LICENSE
procyon_py-0.3.7.dist-info/METADATA
procyon_py-0.3.7.dist-info/WHEEL
procyon_py-0.3.7.dist-info/top_level.txt
procyon_py-0.3.7.dist-info/RECORD
