Metadata-Version: 2.2
Name: procyon-py
Version: 0.3.7
Summary: A terminal based UI library for Python
Home-page: https://github.com/evanlaube/procyon-py
Author: Evan Laube
Author-email: laubeevan@gmail.com
License: GPL 3.0
License-File: LICENSE
Provides-Extra: windows
Requires-Dist: windows-curses; extra == "windows"
Provides-Extra: dev
Requires-Dist: pytest; extra == "dev"
Dynamic: author
Dynamic: author-email
Dynamic: description
Dynamic: description-content-type
Dynamic: home-page
Dynamic: license
Dynamic: provides-extra
Dynamic: summary
